{
  "workflow_completion_time": "2025-11-01T23:32:07.484872",
  "quality_grade_achieved": "A",
  "grade_improvement": true,
  "source_link_coverage": 1.0,
  "source_link_validity": 1.0,
  "coverage_compliant": true,
  "validity_compliant": true,
  "overall_compliance": true,
  "target_achieved": true,
  "key_metrics": {
    "total_key_findings": 5,
    "total_insights": 5,
    "total_recommendations": 5,
    "synthesis_confidence": 0.933,
    "qa_confidence": 0.9400000000000001,
    "report_confidence": 0.9652499999999999
  }
}